sdsstools/__init__.py
sdsstools/_tasks.py
sdsstools/cli.py
sdsstools/configuration.py
sdsstools/daemonizer.py
sdsstools/logger.py
sdsstools/metadata.py
sdsstools/retrier.py
sdsstools/time.py
sdsstools/utils.py
sdsstools/_vendor/__init__.py
sdsstools/_vendor/color_print.py
sdsstools/_vendor/yanny.py
sdsstools/_vendor/toml/__init__.py
sdsstools/_vendor/toml/decoder.py
sdsstools/_vendor/toml/encoder.py
sdsstools/_vendor/toml/ordered.py
sdsstools/_vendor/toml/tz.py
sdsstools-1.9.6.dist-info/METADATA
sdsstools-1.9.6.dist-info/WHEEL
sdsstools-1.9.6.dist-info/entry_points.txt
sdsstools-1.9.6.dist-info/licenses/LICENSE.md
sdsstools-1.9.6.dist-info/RECORD
