Metadata-Version: 2.4
Name: sdsstools
Version: 1.9.6
Summary: Small tools for SDSS products
Project-URL: Homepage, https://github.com/sdss/sdsstools
Project-URL: Repository, https://github.com/sdss/sdsstools
Author-email: José Sánchez-Gallego <gallegoj@uw.edu>
License: BSD-3-Clause
License-File: LICENSE.md
Keywords: astronomy,software
Classifier: Development Status :: 4 - Beta
Classifier: Intended Audience :: Science/Research
Classifier: Natural Language :: English
Classifier: Operating System :: OS Independent
Classifier: Topic :: Documentation :: Sphinx
Classifier: Topic :: Software Development :: Libraries :: Python Modules
Requires-Python: <4,>=3.8
Requires-Dist: daemonocle>=1.0.2
Requires-Dist: invoke>=2.0.0
Requires-Dist: numpy<2,>=1.0.0; python_version >= '3.8' and python_version < '3.10'
Requires-Dist: numpy<3,>=1.26.0; python_version >= '3.10'
Requires-Dist: packaging>=20.4
Requires-Dist: pygments>=2.5.2
Requires-Dist: python-json-logger>=3.2.1
Requires-Dist: pyyaml>=4.0
Requires-Dist: rich>=13.4.2
Requires-Dist: typing-extensions>=4.6.3
